giraffez/__init__.py
giraffez/__main__.py
giraffez/_compat.py
giraffez/_teradata.cp35-win32.pyd
giraffez/_teradatapt.cp35-win32.pyd
giraffez/cmd.py
giraffez/commandline.py
giraffez/config.py
giraffez/connection.py
giraffez/constants.py
giraffez/core.py
giraffez/encoders.py
giraffez/encrypt.py
giraffez/errors.py
giraffez/export.py
giraffez/fmt.py
giraffez/io.py
giraffez/load.py
giraffez/logging.py
giraffez/parser.py
giraffez/secret.py
giraffez/shell.py
giraffez/sql.py
giraffez/types.py
giraffez/utils.py
giraffez-2.0.23.dist-info/DESCRIPTION.rst
giraffez-2.0.23.dist-info/METADATA
giraffez-2.0.23.dist-info/RECORD
giraffez-2.0.23.dist-info/WHEEL
giraffez-2.0.23.dist-info/entry_points.txt
giraffez-2.0.23.dist-info/metadata.json
giraffez-2.0.23.dist-info/top_level.txt
